pacifica_policy-0.8.3-py3.8-nspkg.pth
pacifica/policy/__init__.py
pacifica/policy/__main__.py
pacifica/policy/admin.py
pacifica/policy/admin_cmd.py
pacifica/policy/config.py
pacifica/policy/data_release.py
pacifica/policy/globals.py
pacifica/policy/root.py
pacifica/policy/validation.py
pacifica/policy/wsgi.py
pacifica/policy/events/__init__.py
pacifica/policy/events/rest.py
pacifica/policy/ingest/__init__.py
pacifica/policy/ingest/rest.py
pacifica/policy/reporting/__init__.py
pacifica/policy/reporting/rest.py
pacifica/policy/reporting/transaction/__init__.py
pacifica/policy/reporting/transaction/query_base.py
pacifica/policy/reporting/transaction/transaction_details.py
pacifica/policy/reporting/transaction/transaction_summary.py
pacifica/policy/status/__init__.py
pacifica/policy/status/base.py
pacifica/policy/status/instrument_query.py
pacifica/policy/status/project_query.py
pacifica/policy/status/rest.py
pacifica/policy/status/transaction_query.py
pacifica/policy/status/user_query.py
pacifica/policy/status/instrument/__init__.py
pacifica/policy/status/instrument/by_project_id.py
pacifica/policy/status/instrument/search.py
pacifica/policy/status/project/__init__.py
pacifica/policy/status/project/by_user.py
pacifica/policy/status/project/lookup.py
pacifica/policy/status/project/search.py
pacifica/policy/status/transaction/__init__.py
pacifica/policy/status/transaction/files.py
pacifica/policy/status/transaction/lookup.py
pacifica/policy/status/transaction/search.py
pacifica/policy/status/user/__init__.py
pacifica/policy/status/user/lookup.py
pacifica/policy/status/user/search.py
pacifica/policy/uploader/__init__.py
pacifica/policy/uploader/rest.py
pacifica_policy-0.8.3.dist-info/LICENSE
pacifica_policy-0.8.3.dist-info/METADATA
pacifica_policy-0.8.3.dist-info/WHEEL
pacifica_policy-0.8.3.dist-info/entry_points.txt
pacifica_policy-0.8.3.dist-info/namespace_packages.txt
pacifica_policy-0.8.3.dist-info/top_level.txt
pacifica_policy-0.8.3.dist-info/RECORD
