Metadata-Version: 2.1
Name: pacifica-policy
Version: 0.8.3
Summary: Pacifica Policy Service
Home-page: https://github.com/pacifica/pacifica-policy/
Author: David Brown
Author-email: dmlb2000@gmail.com
License: UNKNOWN
Platform: UNKNOWN
Requires-Dist: backports.functools-lru-cache
Requires-Dist: cherrypy
Requires-Dist: pacifica-namespace
Requires-Dist: python-dateutil
Requires-Dist: requests
